aaman_qjh_mindmap_mcp/__init__.py
aaman_qjh_mindmap_mcp-0.1.5.dist-info/WHEEL
aaman_qjh_mindmap_mcp-0.1.5.dist-info/entry_points.txt
aaman_qjh_mindmap_mcp-0.1.5.dist-info/METADATA
aaman_qjh_mindmap_mcp-0.1.5.dist-info/RECORD
