Metadata-Version: 2.3
Name: aaman-qjh-mindmap-mcp
Version: 0.1.5
Summary: Add your description here
Author: AAAAAAAAAAAAAAAAAAman“
Author-email: AAAAAAAAAAAAAAAAAAman“ <3261232116@qq.com>
Requires-Dist: mcp[cli]>=1.20.0
Requires-Dist: requests>=2.32.5
Requires-Python: >=3.13
